plate_recognition/__init__.py
plate_recognition/recognizer.py
plate_injaz-0.1.dist-info/METADATA
plate_injaz-0.1.dist-info/WHEEL
plate_injaz-0.1.dist-info/top_level.txt
plate_injaz-0.1.dist-info/RECORD
