Metadata-Version: 2.1
Name: plate_injaz
Version: 0.1
Summary: مكتبة للتعرف على لوحات السيارات من الصور باستخدام API Plate Recognizer.
Author: injaz
Author-email: tameenijo@gmail.com
Classifier: Programming Language :: Python :: 3
Classifier: License :: OSI Approved :: MIT License
Classifier: Operating System :: OS Independent
Requires-Dist: requests
Requires-Dist: Flask
Requires-Dist: werkzeug
